dagger/__init__.py
dagger/_version.py
dagger/acc_calibration.py
dagger/altitude.py
dagger/analog.py
dagger/attitude.py
dagger/connect.py
dagger/control.py
dagger/mag_calibration.py
dagger/raw_imu.py
dagger/sensor.py
dagger/set_command.py
dagger/set_raw_rc.py
dagger/utils.py
pluto_dagger-0.1.2.dist-info/AUTHORS.rst
pluto_dagger-0.1.2.dist-info/LICENSE.txt
pluto_dagger-0.1.2.dist-info/METADATA
pluto_dagger-0.1.2.dist-info/WHEEL
pluto_dagger-0.1.2.dist-info/top_level.txt
pluto_dagger-0.1.2.dist-info/RECORD
