Metadata-Version: 2.1
Name: pluto-dagger
Version: 0.1.2
Summary: A Python Wrapper for Pluto Drone Controller
Home-page: https://github.com/rohithvarma3000/dagger/
Author: Nagesh Bansal
Author-email: Nagesh Bansal <nageshbansal59@gmail.com>, Rohith Varma Buddaraju <rohith.varma.buddaraju@gmail.com>, Pratham Kumar Shrivastava <prathamks.email@gmail.com>
License: MIT
Project-URL: Homepage, https://github.com/rohithvarma3000/dagger/
Project-URL: Bug Tracker, https://github.com/rohithvarma3000/dagger/issues
Platform: any
Classifier: Programming Language :: Python :: 3
Classifier: License :: OSI Approved :: MIT License
Classifier: Operating System :: OS Independent
Requires-Python: >=3.7
License-File: LICENSE.txt
License-File: AUTHORS.rst
Requires-Dist: flake8-docstrings
Requires-Dist: pytest
Requires-Dist: pytest-cov
Requires-Dist: sphinx-rtd-theme
Requires-Dist: toml
Requires-Dist: tox
Requires-Dist: yapf
Requires-Dist: importlib-metadata ; python_version < "3.8"
Provides-Extra: testing
Requires-Dist: setuptools ; extra == 'testing'
Requires-Dist: pytest ; extra == 'testing'
Requires-Dist: pytest-cov ; extra == 'testing'
